rtl/fetch/pc.v
// ============================================================
// Module : pc (Program Counter)
// Project : RV32I Pipelined Processor
// Description : Holds the address of the next instruction.
//               Updates every clock cycle to PC+4 (sequential)
//               or to a branch/jump target address.
// ============================================================

module pc (
    input  wire        clk,        // Clock
    input  wire        rst,        // Active-high synchronous reset
    input  wire        stall,      // Hold PC (for hazard stalls) — wire up later
    input  wire [31:0] pc_next,    // Next PC value (PC+4 or branch target)
    output reg  [31:0] pc_out      // Current PC value → goes to instruction memory
);

    always @(posedge clk) begin
        if (rst)
            pc_out <= 32'h00000000;   // On reset, start from address 0
        else if (!stall)
            pc_out <= pc_next;        // Only update if not stalled
    end

endmodule

tb/tb_pc.v
// ============================================================
// Testbench : tb_pc
// Tests : reset behavior, sequential increment, stall, 
//         branch target jump
// ============================================================

`timescale 1ns/1ps

module tb_pc;

    // ---- inputs (driven by testbench) ----
    reg        clk;
    reg        rst;
    reg        stall;
    reg [31:0] pc_next;

    // ---- output (observed) ----
    wire [31:0] pc_out;

    // ---- instantiate the PC ----
    pc uut (
        .clk     (clk),
        .rst     (rst),
        .stall   (stall),
        .pc_next (pc_next),
        .pc_out  (pc_out)
    );

    // ---- clock: 10ns period ----
    initial clk = 0;
    always #5 clk = ~clk;

    // ---- stimulus ----
    initial begin
        $dumpfile("sim/tb_pc.vcd");   // waveform output file
        $dumpvars(0, tb_pc);

        // --- TEST 1: Reset ---
        rst = 1; stall = 0; pc_next = 32'hDEADBEEF;
        @(posedge clk); #1;
        $display("T1 RESET    | pc_out = %h (expect 00000000)", pc_out);

        // --- TEST 2: Sequential increment ---
        rst = 0; pc_next = 32'h00000004;
        @(posedge clk); #1;
        $display("T2 SEQ +4   | pc_out = %h (expect 00000004)", pc_out);

        pc_next = 32'h00000008;
        @(posedge clk); #1;
        $display("T3 SEQ +4   | pc_out = %h (expect 00000008)", pc_out);

        // --- TEST 3: Branch jump ---
        pc_next = 32'h00400080;       // simulate branch target
        @(posedge clk); #1;
        $display("T4 BRANCH   | pc_out = %h (expect 00400080)", pc_out);

        // --- TEST 4: Stall (PC must not change) ---
        stall = 1; pc_next = 32'hFFFFFFFF;
        @(posedge clk); #1;
        $display("T5 STALL    | pc_out = %h (expect 00400080)", pc_out);

        stall = 0;
        @(posedge clk); #1;
        $display("T6 UNSTALL  | pc_out = %h (expect ffffffff)", pc_out);

        $display("-----------------------------");
        $display("PC testbench complete.");
        $finish;
    end

endmodule

riscv_rv32i/riscv_rv32i.sim/sim_1/behav/xsim/dump.vcd
$date
   Wed May 27 20:14:19 2026
$end

$version
  2025.1.0
$end

$timescale
  1ps
$end

$scope module tb_pc $end
$var reg 1 ! clk $end
$var reg 1 " rst $end
$var reg 1 # stall $end
$var reg 32 $ pc_next [31:0] $end
$var wire 32 % pc_out [31:0] $end
$scope module uut $end
$var wire 1 & clk $end
$var wire 1 ' rst $end
$var wire 1 ( stall $end
$var wire 32 ) pc_next [31:0] $end
$var reg 32 * pc_out [31:0] $end
$upscope $end
$upscope $end
$enddefinitions $end

#0
$dumpvars
0!
1"
0#
b11011110101011011011111011101111 $
bx %
0&
1'
0(
b11011110101011011011111011101111 )
bx *
$end

#5000
1!
b0 %
1&
b0 *

#6000
0"
b100 $
0'
b100 )

#10000
0!
0&

#15000
1!
b100 %
1&
b100 *

#16000
b1000 $
b1000 )

#20000
0!
0&

#25000
1!
b1000 %
1&
b1000 *

#26000
b10000000000000010000000 $
b10000000000000010000000 )

#30000
0!
0&

#35000
1!
b10000000000000010000000 %
1&
b10000000000000010000000 *

#36000
1#
b11111111111111111111111111111111 $
1(
b11111111111111111111111111111111 )

#40000
0!
0&

#45000
1!
1&

#46000
0#
0(

#50000
0!
0&

#55000
1!
b11111111111111111111111111111111 %
1&
b11111111111111111111111111111111 *
